mbed_connector_api/__init__.py
mbed_connector_api/connectorError.py
mbed_connector_api/mbed_connector_api.py
mbed_connector_api-1.0.4.dist-info/DESCRIPTION.rst
mbed_connector_api-1.0.4.dist-info/METADATA
mbed_connector_api-1.0.4.dist-info/RECORD
mbed_connector_api-1.0.4.dist-info/WHEEL
mbed_connector_api-1.0.4.dist-info/metadata.json
mbed_connector_api-1.0.4.dist-info/top_level.txt
mdc_api/__init__.py
mdc_api/connectorError.py
mdc_api/mdc_api.py
