Metadata-Version: 2.0
Name: mbed-connector-api
Version: 1.0.4
Summary: REST interface library for mbed Device Connector (connector.mbed.com)
Home-page: http://github.com/armmbed/mbed-connector-api-python
Author: ARM mbed
Author-email: support@mbed.com
License: Apache 2.0
Keywords: ARM mbed connector device mDC mDS ARMmbed
Platform: UNKNOWN
Classifier: Development Status :: 3 - Alpha
Classifier: License :: OSI Approved :: Apache Software License
Classifier: Programming Language :: Python :: 2.7
Classifier: Topic :: Utilities
Classifier: Intended Audience :: Developers
Requires-Dist: requests[security]
